cdk_time_bomb/__init__.py
cdk_time_bomb/py.typed
cdk_time_bomb/_jsii/__init__.py
cdk_time_bomb/_jsii/cdk-time-bomb@1.53.0.jsii.tgz
cdk_time_bomb-1.53.0.dist-info/METADATA
cdk_time_bomb-1.53.0.dist-info/WHEEL
cdk_time_bomb-1.53.0.dist-info/top_level.txt
cdk_time_bomb-1.53.0.dist-info/RECORD
