Metadata-Version: 2.1
Name: cdk-time-bomb
Version: 1.53.0
Summary: Implode your AWS CDK Stack after set amount of time, save money, be happy!
Home-page: https://github.com/jmb12686/cdk-time-bomb#readme
Author: John Belisle<jmb186@gmail.com>
License: MIT
Project-URL: Source, https://github.com/jmb12686/cdk-time-bomb.git
Platform: UNKNOWN
Classifier: Intended Audience :: Developers
Classifier: Operating System :: OS Independent
Classifier: Programming Language :: JavaScript
Classifier: Programming Language :: Python :: 3 :: Only
Classifier: Programming Language :: Python :: 3.6
Classifier: Programming Language :: Python :: 3.7
Classifier: Programming Language :: Python :: 3.8
Classifier: Typing :: Typed
Classifier: Development Status :: 4 - Beta
Classifier: License :: OSI Approved
Requires-Python: >=3.6
Requires-Dist: jsii (<2.0.0,>=1.9.0)
Requires-Dist: publication (>=0.0.3)
Requires-Dist: aws-cdk.aws-events (<2.0.0,>=1.53.0)
Requires-Dist: aws-cdk.aws-events-targets (<2.0.0,>=1.53.0)
Requires-Dist: aws-cdk.aws-iam (<2.0.0,>=1.53.0)
Requires-Dist: aws-cdk.aws-lambda (<2.0.0,>=1.53.0)
Requires-Dist: aws-cdk.core (<2.0.0,>=1.53.0)
